pystatistic/__init__.py
pystatistic-1.0.dist-info/METADATA
pystatistic-1.0.dist-info/WHEEL
pystatistic-1.0.dist-info/top_level.txt
pystatistic-1.0.dist-info/RECORD
