Metadata-Version: 2.1
Name: pystatistic
Version: 1.0
Summary: Count every thing!
Home-page: https://xiaodong.indouyin.cn/python/modules/pystatistic/index.html
Author: DY_XiaoDong
Author-email: xiaodong@indouyin.cn
License: MIT
Platform: UNKNOWN
Requires: colorama
Requires-Dist: colorama
